{
  "response": [
    {
      "maintainer": "Mohammad Kibria",
      "currently_maintained": true,
      "oem": "Xiaomi",
      "device": "garnet",
      "filename": "Lunaris-AOSP-garnet-OFFICIAL-3.4-Core-2025103115.zip",
      "download": "https://sourceforge.net/projects/ghosuto/files/garnet/Lunaris-AOSP-garnet-OFFICIAL-3.4-Core-2025103115.zip/download",
      "timestamp": 1761924523,
      "md5": "88c55f0d0f081793185ed3c113bfd966",
      "sha256": "39f2e51984ccd3998adab34d3f4a66f1a677d7040ed0f84e7b6955950dad916a",
      "size": 2839746221,
      "version": "3.4",
      "buildtype": "user",
      "forum": "https://xdaforums.com/t/rom-16-garnet-official-lunaris-aosp-android-16-for-for-redmi-note-13-pro-5g-poco-x6-5g.4764237/",
      "firmware": "https://xmfirmwareupdater.com/archive/firmware/garnet/",
      "paypal": "https://www.paypal.com/paypalme/kibria05",
      "github": "kibria5",
      "sourceforge": "kibria5",
      "initial_installation_images": []
    }
  ]
}