{
  "response": [
    {
      "maintainer": "kibria5",
      "oem": "Xiaomi",
      "device": "garnet",
      "filename": "Lunaris-AOSP-garnet-OFFICIAL-3.11-VANILLA-2026060812.zip",
      "download": "https://sourceforge.net/projects/ghosuto/files/garnet/vanilla/Lunaris-AOSP-garnet-OFFICIAL-3.11-VANILLA-2026060812.zip/download",
      "timestamp": 1780920197,
      "md5": "52018ac2b8c894012ca89a28db662c97",
      "sha256": "be0ffcc945740702cb7866fae5d6809509441944f6d6f5b9e1e49872b8a6a679",
      "size": 2164191531,
      "version": "3.11",
      "buildtype": "user",
      "forum": "https://xdaforums.com/t/rom-16-garnet-official-lunaris-aosp-android-16-for-for-redmi-note-13-pro-5g-poco-x6-5g.4764237/",
      "gapps": "",
      "firmware": "https://xmfirmwareupdater.com/archive/firmware/garnet/",
      "modem": "",
      "bootloader": "",
      "recovery": "https://sourceforge.net/projects/ghosuto/files/garnet/recovery/recovery.img/download",
      "paypal": "https://www.paypal.com/paypalme/kibria05",
      "telegram": "https://t.me/kibria5",
      "dt": "",
      "common-dt": "",
      "kernel": ""
    }
  ]
}
